justengel_theme/__init__.py
justengel_theme/__meta__.py
justengel_theme/custom_template.py
justengel_theme/extension.py
justengel_theme/global_options.py
justengel_theme/templates/justengel_theme/base.html
justengel_theme/templates/justengel_theme/begin_body.html
justengel_theme/templates/justengel_theme/container.html
justengel_theme/templates/justengel_theme/end_body.html
justengel_theme/templates/justengel_theme/extra_head.html
justengel_theme/templates/justengel_theme/footer.html
justengel_theme/templates/justengel_theme/head.html
justengel_theme/templates/justengel_theme/navbar.html
justengel_theme/templates/justengel_theme/navbar_items.html
justengel_theme/templates/justengel_theme/sidenav.html
justengel_theme/templates/justengel_theme/sidenav_items.html
justengel_theme-1.0.1.dist-info/LICENSE
justengel_theme-1.0.1.dist-info/METADATA
justengel_theme-1.0.1.dist-info/WHEEL
justengel_theme-1.0.1.dist-info/top_level.txt
justengel_theme-1.0.1.dist-info/RECORD
