Metadata-Version: 2.1
Name: justengel-theme
Version: 1.0.1
Summary: Jinja theme capability
Home-page: https://github.com/justengel-web/justengel_theme
Author: Justin Engel
Author-email: jtengel08@gmail.com
License: Proprietary
Download-URL: https://github.com/justengel-web/justengel_theme/archive/v1.0.1.tar.gz
Platform: any
Classifier: Programming Language :: Python
Classifier: Programming Language :: Python :: 3
Classifier: Operating System :: OS Independent
License-File: LICENSE
